fdb_record_layer/__init__.py
fdb_record_layer/core/__init__.py
fdb_record_layer/core/context.py
fdb_record_layer/core/exceptions.py
fdb_record_layer/core/record.py
fdb_record_layer/core/store.py
fdb_record_layer/cursors/__init__.py
fdb_record_layer/cursors/base.py
fdb_record_layer/cursors/result.py
fdb_record_layer/expressions/__init__.py
fdb_record_layer/expressions/base.py
fdb_record_layer/expressions/concat.py
fdb_record_layer/expressions/field.py
fdb_record_layer/expressions/nest.py
fdb_record_layer/expressions/record_type.py
fdb_record_layer/indexes/__init__.py
fdb_record_layer/indexes/builder.py
fdb_record_layer/indexes/count_index.py
fdb_record_layer/indexes/maintainer.py
fdb_record_layer/indexes/rank_index.py
fdb_record_layer/indexes/registry.py
fdb_record_layer/indexes/text_index.py
fdb_record_layer/indexes/value_index.py
fdb_record_layer/metadata/__init__.py
fdb_record_layer/metadata/evolution.py
fdb_record_layer/metadata/index.py
fdb_record_layer/metadata/meta_data_builder.py
fdb_record_layer/metadata/meta_data_store.py
fdb_record_layer/metadata/record_metadata.py
fdb_record_layer/planner/__init__.py
fdb_record_layer/planner/heuristic.py
fdb_record_layer/planner/scan_comparisons.py
fdb_record_layer/planner/cascades/__init__.py
fdb_record_layer/planner/cascades/cost_model.py
fdb_record_layer/planner/cascades/expressions.py
fdb_record_layer/planner/cascades/memo.py
fdb_record_layer/planner/cascades/planner.py
fdb_record_layer/planner/cascades/rule.py
fdb_record_layer/plans/__init__.py
fdb_record_layer/plans/base.py
fdb_record_layer/plans/filter_plan.py
fdb_record_layer/plans/index_plan.py
fdb_record_layer/plans/intersection_plan.py
fdb_record_layer/plans/scan_plan.py
fdb_record_layer/plans/union_plan.py
fdb_record_layer/query/__init__.py
fdb_record_layer/query/comparisons.py
fdb_record_layer/query/components.py
fdb_record_layer/query/predicates.py
fdb_record_layer/query/query.py
fdb_record_layer/relational/__init__.py
fdb_record_layer-0.1.0b2.dist-info/licenses/LICENSE
fdb_record_layer-0.1.0b2.dist-info/METADATA
fdb_record_layer-0.1.0b2.dist-info/WHEEL
fdb_record_layer-0.1.0b2.dist-info/top_level.txt
fdb_record_layer-0.1.0b2.dist-info/RECORD
