Metadata-Version: 2.4
Name: fdb-record-layer
Version: 0.1.0b2
Summary: Python implementation of FoundationDB Record Layer
Author: FDB Record Layer Python Contributors
License: Apache-2.0
Project-URL: Homepage, https://github.com/mirkomikulic/fdb-record-layer-python
Project-URL: Documentation, https://github.com/mirkomikulic/fdb-record-layer-python#readme
Project-URL: Repository, https://github.com/mirkomikulic/fdb-record-layer-python
Classifier: Development Status :: 3 - Alpha
Classifier: Intended Audience :: Developers
Classifier: License :: OSI Approved :: Apache Software License
Classifier: Programming Language :: Python :: 3
Classifier: Programming Language :: Python :: 3.10
Classifier: Programming Language :: Python :: 3.11
Classifier: Programming Language :: Python :: 3.12
Classifier: Programming Language :: Python :: 3.13
Classifier: Topic :: Database
Requires-Python: >=3.10
License-File: LICENSE
Requires-Dist: foundationdb>=7.1.0
Requires-Dist: protobuf>=3.20.0
Requires-Dist: typing-extensions>=4.0.0
Provides-Extra: sql
Requires-Dist: lark>=1.0.0; extra == "sql"
Provides-Extra: grpc
Requires-Dist: grpcio>=1.50.0; extra == "grpc"
Provides-Extra: dev
Requires-Dist: pytest>=7.0.0; extra == "dev"
Requires-Dist: pytest-asyncio>=0.21.0; extra == "dev"
Requires-Dist: mypy>=1.0.0; extra == "dev"
Requires-Dist: ruff>=0.1.0; extra == "dev"
Provides-Extra: all
Requires-Dist: fdb-record-layer[dev,grpc,sql]; extra == "all"
Dynamic: license-file
